{"id": 15069, "title": "Diet and Health; With Key to the Calories", "authors": [{"name": "Peters, Lulu Hunt", "birth_year": 1873, "death_year": 1930}], "summaries": ["\"Diet and Health; With Key to the Calories\" by Lulu Hunt Peters is a health and diet guide written in the early 20th century. It focuses on educating readers about weight management, providing insights and practical advice on both gaining and losing weight through dietary choices and exercise. The book is aimed particularly at those struggling with overweight issues while also addressing the concerns of individuals looking to gain weight in a healthy manner.  The opening of the text introduces the author's apologetic and somewhat humorous tone, establishing her intent to offer practical dietary advice while hinting at the multifaceted nature of weight management. Peters explains the complexity of food knowledge as crucial for anyone wishing to address their weight, whether they seek to lose or gain it. Readers are informed about a simple formula to calculate ideal weight based on height, as well as the importance of understanding calories\u2014setting the stage for a more in-depth exploration of diet and nutrition. Overall, the beginning illustrates Peters' candid style and her determination to provide useful insights for readers, engaging them in discussions about health and wellness in a humorous yet informative way. (This is an automatically generated summary.)"], "editors": [], "translators": [], "subjects": ["Diet"], "bookshelves": ["Bestsellers, American, 1895-1923", "Category: Health & Medicine", "Category: How To ...", "Category: Nutrition", "Cookbooks and Cooking", "Technology"], "languages": ["en"], "copyright": false, "media_type": "Text", "formats": {"text/html": "https://www.gutenberg.org/ebooks/15069.html.images", "application/epub+zip": "https://www.gutenberg.org/ebooks/15069.epub3.images", "application/x-mobipocket-ebook": "https://www.gutenberg.org/ebooks/15069.kf8.images", "application/rdf+xml": "https://www.gutenberg.org/ebooks/15069.rdf", "image/jpeg": "https://www.gutenberg.org/cache/epub/15069/pg15069.cover.medium.jpg", "application/octet-stream": "https://www.gutenberg.org/files/15069/15069-8.zip", "text/plain; charset=utf-8": "https://www.gutenberg.org/ebooks/15069.txt.utf-8", "text/plain; charset=us-ascii": "https://www.gutenberg.org/files/15069/15069-8.txt"}, "download_count": 773}