{"id": 1633, "title": "The Brick Moon, and Other Stories", "authors": [{"name": "Hale, Edward Everett", "birth_year": 1822, "death_year": 1909}], "summaries": ["\"The Brick Moon, and Other Stories\" by Edward Everett Hale is a collection published in 1899. The title novella, originally serialized in 1869, tells the story of a massive brick sphere designed as a navigational aid that accidentally launches into orbit with people aboard. This pioneering work of speculative fiction contains the first known fictional descriptions of both an artificial satellite and a space station, remarkably anticipating modern concepts of orbital navigation systems. (This is an automatically generated summary.)"], "editors": [], "translators": [], "subjects": ["Short stories", "United States -- Social life and customs -- 19th century -- Fiction"], "bookshelves": ["Category: American Literature", "Category: Science-Fiction & Fantasy", "Category: Short Stories"], "languages": ["en"], "copyright": false, "media_type": "Text", "formats": {"text/html": "https://www.gutenberg.org/ebooks/1633.html.images", "application/epub+zip": "https://www.gutenberg.org/ebooks/1633.epub3.images", "application/x-mobipocket-ebook": "https://www.gutenberg.org/ebooks/1633.kf8.images", "application/rdf+xml": "https://www.gutenberg.org/ebooks/1633.rdf", "image/jpeg": "https://www.gutenberg.org/cache/epub/1633/pg1633.cover.medium.jpg", "application/octet-stream": "https://www.gutenberg.org/files/1633/1633-0.zip", "text/plain; charset=utf-8": "https://www.gutenberg.org/ebooks/1633.txt.utf-8", "text/plain; charset=us-ascii": "https://www.gutenberg.org/files/1633/1633-0.txt"}, "download_count": 616}