{"id": 18531, "title": "Timothy's Quest: A Story for Anybody, Young or Old, Who Cares to Read It", "authors": [{"name": "Wiggin, Kate Douglas Smith", "birth_year": 1856, "death_year": 1923}], "summaries": ["\"Timothy's Quest\" by Kate Douglas Smith Wiggin is a children's novel written in the late 19th century. The story revolves around a young boy named Timothy Jessup, who takes on parental responsibilities for his baby sister, Lady Gay, after their mother, Flossy Morrison, passes away. Faced with the harsh realities of life in a dilapidated urban environment, Timothy\u2019s quest is to find a loving home for himself and Lady Gay, showcasing themes of love, resilience, and the search for belonging.  At the start of the narrative, Flossy Morrison has recently died, leaving behind her two children, Timothy and Lady Gay. The opening describes the dreary and impoverished setting of Minerva Court, where Timothy lives. As two women discuss the fate of the children, little Timothy quietly resolves to save Lady Gay from being taken to an orphan asylum. He devises a plan to escape with her, embarking on a daring journey with their loyal dog, Rags. Timothy dreams of finding a mother who will love Lady Gay as he does, setting the stage for their adventures. (This is an automatically generated summary.)"], "editors": [], "translators": [], "subjects": ["Orphans -- Juvenile fiction"], "bookshelves": ["Category: Adventure", "Category: American Literature", "Category: Children & Young Adult Reading", "Category: Novels", "Children's Literature"], "languages": ["en"], "copyright": false, "media_type": "Text", "formats": {"text/html": "https://www.gutenberg.org/ebooks/18531.html.images", "application/epub+zip": "https://www.gutenberg.org/ebooks/18531.epub3.images", "application/x-mobipocket-ebook": "https://www.gutenberg.org/ebooks/18531.kf8.images", "application/rdf+xml": "https://www.gutenberg.org/ebooks/18531.rdf", "image/jpeg": "https://www.gutenberg.org/cache/epub/18531/pg18531.cover.medium.jpg", "application/octet-stream": "https://www.gutenberg.org/files/18531/18531-8.zip", "text/plain; charset=utf-8": "https://www.gutenberg.org/ebooks/18531.txt.utf-8", "text/plain; charset=us-ascii": "https://www.gutenberg.org/files/18531/18531-8.txt"}, "download_count": 274}