{"id": 18559, "title": "The Child's Day", "authors": [{"name": "Hutchinson, Woods", "birth_year": 1862, "death_year": 1930}], "summaries": ["\"The Child's Day\" by Woods Hutchinson is an educational work aimed at children, likely written in the early 20th century. This book provides insights into health and well-being through a discussion of the daily routine of children, emphasizing the importance of various activities\u2014such as bathing, eating nutritious meals, playing outdoors, and maintaining good hygiene. Its goal is to teach young readers how to protect their health and make sensible lifestyle choices that contribute to their overall growth and happiness.  At the start of the book, the author sets a positive tone by describing the joy of waking up on a bright spring morning and appreciating the sunlight, which plays a critical role in health. The subsequent sections cover the significance of morning routines, including stretching, bathing, and dressing, intertwined with lessons about the body's functions and requirements. The opening introduces the concept of the \"wonderful coat\"\u2014the skin\u2014and explains its functions, promoting an understanding of personal hygiene. Overall, the opening portion establishes a foundation for health education that is engaging and accessible to its young audience. (This is an automatically generated summary.)"], "editors": [], "translators": [], "subjects": ["Child care"], "bookshelves": ["Category: Children & Young Adult Reading", "Category: Health & Medicine", "Category: Teaching & Education"], "languages": ["en"], "copyright": false, "media_type": "Text", "formats": {"text/html": "https://www.gutenberg.org/ebooks/18559.html.images", "application/epub+zip": "https://www.gutenberg.org/ebooks/18559.epub3.images", "application/x-mobipocket-ebook": "https://www.gutenberg.org/ebooks/18559.kf8.images", "application/rdf+xml": "https://www.gutenberg.org/ebooks/18559.rdf", "image/jpeg": "https://www.gutenberg.org/cache/epub/18559/pg18559.cover.medium.jpg", "application/octet-stream": "https://www.gutenberg.org/files/18559/18559-8.zip", "text/plain; charset=utf-8": "https://www.gutenberg.org/ebooks/18559.txt.utf-8", "text/plain; charset=us-ascii": "https://www.gutenberg.org/files/18559/18559-8.txt"}, "download_count": 337}