{"id": 21136, "title": "For Fortune and Glory: A Story of the Soudan War", "authors": [{"name": "Hough, Lewis", "birth_year": null, "death_year": null}], "summaries": ["\"For Fortune and Glory: A Story of the Soudan War\" by Lewis Hough is a historical novel written in the late 19th century. The story interweaves themes of adventure, familial duty, and colonial conflict, centering on young Harry Forsyth who navigates personal challenges amidst the backdrop of the Soudan War. As events unfold, Harry's quest for understanding his family's past and securing his future in a rapidly changing world drives the narrative.  At the start of the book, readers meet Harry Forsyth as he returns home from boarding school, eager to reunite with his family. The opening chapters reveal his affection for his mother and sister, as well as the introduction of a mysterious uncle, Ralph Burke, who has returned from living among \"wild men\" in the desert and brings with him secrets that could alter Harry\u2019s life. The story hints at dark familial secrets, particularly regarding a missing will linked to his uncle that has lingering implications for the family's fortune. This blend of personal and historical exploration sets the stage for adventure and moral dilemmas to come as the characters confront their legacies amidst the backdrop of war. (This is an automatically generated summary.)"], "editors": [], "translators": [], "subjects": ["Great Britain -- History, Military -- 19th century -- Fiction", "Sudan -- History -- 1881-1899 -- Fiction"], "bookshelves": ["Category: Adventure", "Category: British Literature", "Category: Historical Novels"], "languages": ["en"], "copyright": false, "media_type": "Text", "formats": {"text/html": "https://www.gutenberg.org/ebooks/21136.html.images", "application/epub+zip": "https://www.gutenberg.org/ebooks/21136.epub3.images", "application/x-mobipocket-ebook": "https://www.gutenberg.org/ebooks/21136.kf8.images", "application/rdf+xml": "https://www.gutenberg.org/ebooks/21136.rdf", "image/jpeg": "https://www.gutenberg.org/cache/epub/21136/pg21136.cover.medium.jpg", "application/octet-stream": "https://www.gutenberg.org/files/21136/21136-h.zip", "text/plain; charset=utf-8": "https://www.gutenberg.org/ebooks/21136.txt.utf-8", "text/plain; charset=us-ascii": "https://www.gutenberg.org/files/21136/21136.txt"}, "download_count": 782}