{"id": 2562, "title": "The Clouds", "authors": [{"name": "Aristophanes", "birth_year": -450, "death_year": -388}], "summaries": ["\"The Clouds\" by Aristophanes is a Greek comedy play written in 423 BC. This satirical work lampoons intellectual fashions in classical Athens, centering on a debt-ridden father who enrolls in Socrates' school\u2014The Thinkery\u2014to learn how to twist arguments and outwit his creditors. When he proves too old to learn, his son must take his place. Considered the world's first \"comedy of ideas,\" the play remains notorious for its caricature of Socrates, later cited as contributing to the philosopher's trial and execution. (This is an automatically generated summary.)"], "editors": [], "translators": [{"name": "Hickie, W. J.", "birth_year": null, "death_year": null}], "subjects": ["Aristophanes -- Translations into English", "Classical literature", "Comedy plays", "Greek drama (Comedy) -- Translations into English", "Rhetoric -- Study and teaching -- Drama"], "bookshelves": ["Banned Books from Anne Haight's list", "Category: Classics of Literature", "Category: History - Ancient", "Category: Plays/Films/Dramas", "Classical Antiquity"], "languages": ["en"], "copyright": false, "media_type": "Text", "formats": {"text/html": "https://www.gutenberg.org/ebooks/2562.html.images", "text/html; charset=us-ascii": "https://www.gutenberg.org/files/2562/2562-h/2562-h.htm", "application/epub+zip": "https://www.gutenberg.org/ebooks/2562.epub3.images", "application/x-mobipocket-ebook": "https://www.gutenberg.org/ebooks/2562.kf8.images", "application/rdf+xml": "https://www.gutenberg.org/ebooks/2562.rdf", "image/jpeg": "https://www.gutenberg.org/cache/epub/2562/pg2562.cover.medium.jpg", "application/octet-stream": "https://www.gutenberg.org/cache/epub/2562/pg2562-h.zip", "text/plain; charset=utf-8": "https://www.gutenberg.org/ebooks/2562.txt.utf-8", "text/plain; charset=us-ascii": "https://www.gutenberg.org/files/2562/2562.txt"}, "download_count": 1208}