{"id": 27772, "title": "Le Roman Comique", "authors": [{"name": "Scarron, Paul", "birth_year": 1610, "death_year": 1660}], "summaries": ["\"Le Roman Comique\" by Paul Scarron is a novel published in two parts in 1651 and 1657. A traveling theater troupe arrives in Le Mans, launching a series of comic and adventurous escapades. The narrative weaves between present-day theatrical mishaps and embedded tales of love and intrigue, including the romantic flight of Garrigues and Mlle de La Boissi\u00e8re. At its center is Ragotin, a vain and ridiculous dwarf whose farcical misadventures provide comic relief. Scarron died while working on the third part, leaving this vibrant portrait of seventeenth-century theatrical life unfinished. (This is an automatically generated summary.)"], "editors": [], "translators": [], "subjects": ["French fiction -- 17th century"], "bookshelves": ["Category: Classics of Literature", "Category: French Literature", "Category: Humour", "Category: Novels", "FR Humour"], "languages": ["fr"], "copyright": false, "media_type": "Text", "formats": {"text/html": "https://www.gutenberg.org/ebooks/27772.html.images", "application/epub+zip": "https://www.gutenberg.org/ebooks/27772.epub3.images", "application/x-mobipocket-ebook": "https://www.gutenberg.org/ebooks/27772.kf8.images", "application/rdf+xml": "https://www.gutenberg.org/ebooks/27772.rdf", "image/jpeg": "https://www.gutenberg.org/cache/epub/27772/pg27772.cover.medium.jpg", "application/octet-stream": "https://www.gutenberg.org/files/27772/27772-8.zip", "text/plain; charset=utf-8": "https://www.gutenberg.org/ebooks/27772.txt.utf-8", "text/plain; charset=us-ascii": "https://www.gutenberg.org/files/27772/27772-8.txt"}, "download_count": 495}