{"id": 29757, "title": "The Story of a Tinder-box", "authors": [{"name": "Tidy, Charles Meymott", "birth_year": 1843, "death_year": 1892}], "summaries": ["\"The Story of a Tinder-box\" by Charles Meymott Tidy is a collection of scientific lectures designed for a juvenile audience, written during the late 19th century. The book explores the history and methods of producing fire, from ancient techniques to the advent of modern matches. Tidy employs engaging language and practical demonstrations to make complex scientific concepts accessible and intriguing for young readers.  Throughout the book, Tidy narrates the evolution of fire-starting tools, beginning with primitive methods like friction and moving on to the invention of the tinder-box. He describes the chemical principles behind the materials used, such as phosphorus and sulfur, and explains the processes involved in igniting them. Each lecture builds upon the previous one, ultimately comparing the venerable tinder-box with contemporary fire-making devices, illustrating the transitions in technology and highlighting the enduring significance of understanding these scientific principles in everyday life. (This is an automatically generated summary.)"], "editors": [], "translators": [], "subjects": ["Combustion"], "bookshelves": ["Category: Children & Young Adult Reading", "Category: History - Other", "Category: Science - Chemistry/Biochemistry", "Category: Science - Physics"], "languages": ["en"], "copyright": false, "media_type": "Text", "formats": {"text/html": "https://www.gutenberg.org/ebooks/29757.html.images", "application/epub+zip": "https://www.gutenberg.org/ebooks/29757.epub3.images", "application/x-mobipocket-ebook": "https://www.gutenberg.org/ebooks/29757.kf8.images", "application/rdf+xml": "https://www.gutenberg.org/ebooks/29757.rdf", "image/jpeg": "https://www.gutenberg.org/cache/epub/29757/pg29757.cover.medium.jpg", "application/octet-stream": "https://www.gutenberg.org/files/29757/29757-8.zip", "text/plain; charset=utf-8": "https://www.gutenberg.org/ebooks/29757.txt.utf-8", "text/plain; charset=us-ascii": "https://www.gutenberg.org/files/29757/29757-8.txt"}, "download_count": 238}