{"id": 34726, "title": "Vas\u00e1rnapi K\u00f6nyv. 1914. Els\u0151 f\u00e9l\u00e9v 17. f\u00fczet", "authors": [{"name": "Anonymous", "birth_year": null, "death_year": null}], "summaries": ["\"Vas\u00e1rnapi K\u00f6nyv. 1914. Els\u0151 f\u00e9l\u00e9v 17. f\u00fczet\" by Anonymous is a collection of essays and articles written in the early 20th century. The book covers various topics such as cooperation in economic life, the benefits of massage, salt production in Africa, wire weaving, and a brief biography of Nicolaus Copernicus, highlighting the significance of scientific discoveries. This eclectic assortment reflects both practical knowledge and historical context, making it a fascinating glimpse into the mindset and everyday concerns of the time.  In this volume, the author discusses the importance of collaboration and cooperation among individuals to achieve greater economic success, emphasizing that working together allows for shared resources and increased efficiency. It also delves into the art and benefits of massage, explaining its therapeutic effects on health. The section on salt production illustrates the economic relevance of salt in Africa, detailing its extraction and trade. Additionally, the book provides insights into the process of wire weaving and concludes with an engaging account of Copernicus's life and revolutionary contributions to astronomy, illustrating his struggles and achievements in a persistent quest for knowledge. (This is an automatically generated summary.)"], "editors": [{"name": "\u00c1rkay, K\u00e1lm\u00e1n", "birth_year": null, "death_year": null}], "translators": [], "subjects": ["Periodicals"], "bookshelves": ["Category: Biographies", "Category: Economics", "Category: Essays, Letters & Speeches", "Category: Health & Medicine", "Category: Science - Physics"], "languages": ["hu"], "copyright": false, "media_type": "Text", "formats": {"text/html": "https://www.gutenberg.org/ebooks/34726.html.images", "application/epub+zip": "https://www.gutenberg.org/ebooks/34726.epub3.images", "application/x-mobipocket-ebook": "https://www.gutenberg.org/ebooks/34726.kf8.images", "application/rdf+xml": "https://www.gutenberg.org/ebooks/34726.rdf", "image/jpeg": "https://www.gutenberg.org/cache/epub/34726/pg34726.cover.medium.jpg", "application/octet-stream": "https://www.gutenberg.org/files/34726/34726-0.zip", "text/plain; charset=utf-8": "https://www.gutenberg.org/ebooks/34726.txt.utf-8", "text/plain; charset=us-ascii": "https://www.gutenberg.org/files/34726/34726-0.txt"}, "download_count": 170}