{"id": 37030, "title": "Some Famous Problems of the Theory of Numbers and in Particular Waring's Problem: An Inaugural Lecture delivered before the University of Oxford", "authors": [{"name": "Hardy, G. H. (Godfrey Harold)", "birth_year": 1877, "death_year": 1947}], "summaries": [], "editors": [], "translators": [], "subjects": ["Number theory"], "bookshelves": ["Mathematics"], "languages": ["en"], "copyright": false, "media_type": "Text", "formats": {"application/pdf": "https://www.gutenberg.org/files/37030/37030-pdf.pdf", "application/rdf+xml": "https://www.gutenberg.org/ebooks/37030.rdf", "application/prs.tex": "https://www.gutenberg.org/files/37030/37030-t/37030-t.tex", "image/jpeg": "https://www.gutenberg.org/cache/epub/37030/pg37030.cover.medium.jpg", "application/octet-stream": "https://www.gutenberg.org/files/37030/37030-pdf.zip"}, "download_count": 171}