{"id": 37869, "title": "De Ellendigen (Deel 4 van 5)", "authors": [{"name": "Hugo, Victor", "birth_year": 1802, "death_year": 1885}], "summaries": ["\"De Ellendigen (Deel 4 van 5)\" by Victor Hugo is a French epic historical novel first published in 1862. This fourth volume continues the story of ex-convict Jean Valjean's struggle for redemption against the backdrop of French society. Set between 1815 and the 1832 June Rebellion in Paris, the novel explores themes of law and grace, justice and mercy, while following the intersecting lives of unforgettable characters. Hugo examines poverty's degradation, social condemnation, and humanity's journey from darkness to light. (This is an automatically generated summary.)"], "editors": [], "translators": [], "subjects": ["Epic literature", "Ex-convicts -- Fiction", "Historical fiction", "Orphans -- Fiction", "Paris (France) -- Fiction"], "bookshelves": ["Category: Classics of Literature", "Category: French Literature", "Category: Historical Novels"], "languages": ["nl"], "copyright": false, "media_type": "Text", "formats": {"text/html": "https://www.gutenberg.org/ebooks/37869.html.images", "application/epub+zip": "https://www.gutenberg.org/ebooks/37869.epub3.images", "application/x-mobipocket-ebook": "https://www.gutenberg.org/ebooks/37869.kf8.images", "text/plain; charset=us-ascii": "https://www.gutenberg.org/ebooks/37869.txt.utf-8", "application/rdf+xml": "https://www.gutenberg.org/ebooks/37869.rdf", "image/jpeg": "https://www.gutenberg.org/cache/epub/37869/pg37869.cover.medium.jpg", "application/octet-stream": "https://www.gutenberg.org/files/37869/37869-8.zip"}, "download_count": 422}