{"id": 37928, "title": "Gas Burners Old and New: A historical and descriptive treatise on the progress of invention in gas lighting, embracing an account of the theory of luminous combustion", "authors": [{"name": "Merriman, Owen", "birth_year": null, "death_year": null}], "summaries": ["\"Gas Burners Old and New\" by Owen Merriman is a historical and descriptive treatise written in the late 19th century. The work delves into the development and improvements of gas lighting and burners, addressing both the consumer's and producer's perspective on gas usage. Merriman aims to increase public understanding of this technology while presenting an engaging account of the advances in gas burner designs over time.  The beginning of the treatise introduces the critical relationship between gas manufacturers and consumers, outlining how efficient gas burners can dramatically affect lighting quality and gas consumption costs. Merriman expresses a desire to explain the principles of gas combustion and highlight the evolution of various burners, starting with simple designs like the early gas burner examples. He also notes the historical skepticism surrounding gas lighting and acknowledges the significant progress made in enhancing the efficiency of gas burners compared to their predecessors. (This is an automatically generated summary.)"], "editors": [], "translators": [], "subjects": ["Gas-burners"], "bookshelves": ["Category: Engineering & Technology", "Category: History - Modern (1750+)", "Category: Science - Chemistry/Biochemistry"], "languages": ["en"], "copyright": false, "media_type": "Text", "formats": {"text/html": "https://www.gutenberg.org/ebooks/37928.html.images", "application/epub+zip": "https://www.gutenberg.org/ebooks/37928.epub3.images", "application/x-mobipocket-ebook": "https://www.gutenberg.org/ebooks/37928.kf8.images", "text/plain; charset=us-ascii": "https://www.gutenberg.org/ebooks/37928.txt.utf-8", "application/rdf+xml": "https://www.gutenberg.org/ebooks/37928.rdf", "image/jpeg": "https://www.gutenberg.org/cache/epub/37928/pg37928.cover.medium.jpg", "application/octet-stream": "https://www.gutenberg.org/files/37928/37928-8.zip"}, "download_count": 287}