{"id": 40058, "title": "The Life of Florence Nightingale, vol. 2 of 2", "authors": [{"name": "Cook, Edward Tyas, Sir", "birth_year": 1857, "death_year": 1919}], "summaries": ["\"The Life of Florence Nightingale, vol. 2 of 2\" by Sir Edward Tyas Cook is a historical account written in the early 20th century. The book chronicles the life and impact of Florence Nightingale, focusing on her contributions to nursing and public health, particularly during the latter half of the 19th century. It details her tireless efforts in reforming military healthcare and nursing practices, as well as her influence on the British Army's sanitation policies, particularly regarding the health of soldiers in India.  At the start of the second volume, the narrative captures Nightingale's profound sense of loss following the tragedies of her close associates, Sidney Herbert and Arthur Hugh Clough. Despite her grief, she redirects her energy towards influential public health reforms, including the establishment of a Royal Commission focused on the health of the British Army in India. The text introduces themes of personal struggle and determination, emphasizing Nightingale's exceptional resilience and commitment to improving sanitary conditions for soldiers, reflecting both her pioneering spirit in nursing and her stature as a reformer in public health. (This is an automatically generated summary.)"], "editors": [], "translators": [], "subjects": ["Nightingale, Florence, 1820-1910"], "bookshelves": ["Category: Biographies", "Category: Health & Medicine", "Category: History - British"], "languages": ["en"], "copyright": false, "media_type": "Text", "formats": {"text/html": "https://www.gutenberg.org/ebooks/40058.html.images", "application/epub+zip": "https://www.gutenberg.org/ebooks/40058.epub3.images", "application/x-mobipocket-ebook": "https://www.gutenberg.org/ebooks/40058.kf8.images", "text/plain; charset=us-ascii": "https://www.gutenberg.org/ebooks/40058.txt.utf-8", "application/rdf+xml": "https://www.gutenberg.org/ebooks/40058.rdf", "image/jpeg": "https://www.gutenberg.org/cache/epub/40058/pg40058.cover.medium.jpg", "application/octet-stream": "https://www.gutenberg.org/cache/epub/40058/pg40058-h.zip"}, "download_count": 4655}