{"id": 43625, "title": "The Survey, Volume 30, Number 1, April 5, 1913", "authors": [{"name": "Various", "birth_year": null, "death_year": null}], "summaries": ["\"The Survey, Volume 30, Number 1, April 5, 1913\" by Various is a historical publication written in the early 20th century. This edition focuses on various social and humanitarian concerns in society during its time, particularly in the context of disaster relief, social legislation, and public health issues. The articles within likely provide insights into the social dynamics, challenges, and responses to events such as natural disasters, as well as broader themes surrounding social responsibility and reform.  The opening of this volume discusses the prompt response to natural disasters in the Mississippi Valley, detailing the efficient organizational efforts of the Red Cross and other charitable institutions in administering relief. It highlights the immediate deployment of trained workers in response to the devastation caused by floods and tornadoes, and emphasizes the importance of careful previous planning in ensuring effective aid. Additionally, it touches on the anticipated challenges of sanitation and ongoing support needed for recovery in affected communities, setting the stage for a broader discourse on the responsibilities of society and government in times of crisis. (This is an automatically generated summary.)"], "editors": [{"name": "Kellogg, Paul Underwood", "birth_year": 1879, "death_year": 1958}], "translators": [], "subjects": ["Charities -- Periodicals", "Social problems -- Periodicals", "United States -- Social conditions -- Periodicals"], "bookshelves": ["Category: Environmental Issues", "Category: Health & Medicine", "Category: History - Modern (1750+)", "Category: Reports & Conference Proceedings", "Category: Sociology"], "languages": ["en"], "copyright": false, "media_type": "Text", "formats": {"text/html": "https://www.gutenberg.org/ebooks/43625.html.images", "application/epub+zip": "https://www.gutenberg.org/ebooks/43625.epub3.images", "application/x-mobipocket-ebook": "https://www.gutenberg.org/ebooks/43625.kf8.images", "text/plain; charset=us-ascii": "https://www.gutenberg.org/ebooks/43625.txt.utf-8", "application/rdf+xml": "https://www.gutenberg.org/ebooks/43625.rdf", "image/jpeg": "https://www.gutenberg.org/cache/epub/43625/pg43625.cover.medium.jpg", "application/octet-stream": "https://www.gutenberg.org/cache/epub/43625/pg43625-h.zip"}, "download_count": 366}