{"id": 46640, "title": "Les femmes et les livres", "authors": [{"name": "Cim, Albert", "birth_year": 1845, "death_year": 1924}], "summaries": ["\"Les femmes et les livres\" by Albert Cim is a literary treatise written in the early 20th century. The work explores the complex relationship between women and literature, focusing on both bibliophobes (women who disdain books) as well as bibliophiles (women who cherish them). Cim aims to challenge historical perceptions that portray women as instinctual enemies of literature, while also highlighting notable exceptions among women who have embraced reading and book collection.  At the start of the text, Cim introduces the premise of his exploration by referencing historical bibliographers who have been excessively critical of women\u2019s supposed distaste for books. He discusses the opinions of various scholars and literary figures who have claimed that women are fundamentally antagonistic to literature, often presenting humorous anecdotes and historical examples. Cim makes it clear that he will methodically review both the \"enemies of books\" and the \"friends of books,\" setting the stage for a deeper examination of women's roles in the domain of literature throughout history. (This is an automatically generated summary.)"], "editors": [], "translators": [], "subjects": ["Women -- Biography", "Women book collectors"], "bookshelves": ["Category: Essays, Letters & Speeches", "Category: French Literature", "FR Femmes"], "languages": ["fr"], "copyright": false, "media_type": "Text", "formats": {"text/html": "https://www.gutenberg.org/ebooks/46640.html.images", "application/epub+zip": "https://www.gutenberg.org/ebooks/46640.epub3.images", "application/x-mobipocket-ebook": "https://www.gutenberg.org/ebooks/46640.kf8.images", "text/plain; charset=us-ascii": "https://www.gutenberg.org/ebooks/46640.txt.utf-8", "application/rdf+xml": "https://www.gutenberg.org/ebooks/46640.rdf", "image/jpeg": "https://www.gutenberg.org/cache/epub/46640/pg46640.cover.medium.jpg", "application/octet-stream": "https://www.gutenberg.org/cache/epub/46640/pg46640-h.zip"}, "download_count": 426}