{"id": 47268, "title": "Alte Nester: Zwei B\u00fccher Lebensgeschichten", "authors": [{"name": "Raabe, Wilhelm", "birth_year": 1831, "death_year": 1910}], "summaries": ["\"Alte Nester: Zwei B\u00fccher Lebensgeschichten\" by Wilhelm Raabe is a novel written between 1877-1879. Berlin philologist Fritz Langreuter recounts his childhood near the Weser River, where he and four friends built tree nests and dreamed together at Schloss Werden castle. Years later, tragedy, exile, and lost fortunes have scattered the group across continents. When paths finally converge again in their homeland, old bonds are tested and the impossible question emerges: can anyone truly return to the nests of childhood? (This is an automatically generated summary.)"], "editors": [], "translators": [], "subjects": ["German literature -- 19th century"], "bookshelves": ["Category: German Literature", "Category: Novels"], "languages": ["de"], "copyright": false, "media_type": "Text", "formats": {"text/html": "https://www.gutenberg.org/ebooks/47268.html.images", "application/epub+zip": "https://www.gutenberg.org/ebooks/47268.epub3.images", "application/x-mobipocket-ebook": "https://www.gutenberg.org/ebooks/47268.kf8.images", "application/rdf+xml": "https://www.gutenberg.org/ebooks/47268.rdf", "image/jpeg": "https://www.gutenberg.org/cache/epub/47268/pg47268.cover.medium.jpg", "application/octet-stream": "https://www.gutenberg.org/cache/epub/47268/pg47268-h.zip", "text/plain; charset=utf-8": "https://www.gutenberg.org/ebooks/47268.txt.utf-8", "text/plain; charset=us-ascii": "https://www.gutenberg.org/files/47268/47268-0.txt"}, "download_count": 332}