{"id": 4968, "title": "Les Cinq Cents Millions De La B\u00e9gum", "authors": [{"name": "Verne, Jules", "birth_year": 1828, "death_year": 1905}], "summaries": ["\"Les Cinq Cents Millions De La B\u00e9gum\" by Jules Verne is a novel published in 1879. Two men inherit a massive fortune from a wealthy B\u00e9gum\u2014a French doctor and a German professor. The Frenchman builds France-Ville, an ideal city based on hygiene and modern urban planning. The German constructs Stahlstadt, a steel fortress dedicated to heavy industry. When Marcel, a young Alsatian, infiltrates the German's city as a spy, he discovers a sinister plot that threatens France-Ville's very existence. (This is an automatically generated summary.)"], "editors": [], "translators": [], "subjects": ["Distribution of decedents' estates -- Fiction", "New towns -- Fiction", "Oregon -- Fiction", "Science fiction"], "bookshelves": ["Category: French Literature", "Category: Novels", "Category: Science-Fiction & Fantasy", "FR Litt\u00e9rature", "FR Science fiction"], "languages": ["fr"], "copyright": false, "media_type": "Text", "formats": {"text/html": "https://www.gutenberg.org/ebooks/4968.html.images", "application/epub+zip": "https://www.gutenberg.org/ebooks/4968.epub3.images", "application/x-mobipocket-ebook": "https://www.gutenberg.org/ebooks/4968.kf8.images", "application/rdf+xml": "https://www.gutenberg.org/ebooks/4968.rdf", "image/jpeg": "https://www.gutenberg.org/cache/epub/4968/pg4968.cover.medium.jpg", "application/octet-stream": "https://www.gutenberg.org/files/4968/4968-0.zip", "text/plain; charset=utf-8": "https://www.gutenberg.org/ebooks/4968.txt.utf-8", "text/plain; charset=us-ascii": "https://www.gutenberg.org/files/4968/4968-0.txt"}, "download_count": 363}