{"id": 51646, "title": "The War Book of the German General Staff: Being \"The Usages of War on Land\" Issued by the Great General Staff of the German Army", "authors": [{"name": "Prussia (Germany). Armee. Grosser Generalstab. Kriegsgeschichtliche Abteilung II", "birth_year": null, "death_year": null}], "summaries": ["\"The War Book of the German General Staff\" is a historical account written in the early 20th century. This work comprises a translation of \"Kriegsbrauch im Landkriege,\" a manual issued by the German General Staff for military instruction. The book likely delves into the strategies, usages, and moral considerations surrounding warfare, particularly as conceived by the German military tradition.   At the start of the text, the critical introduction establishes the authoritative nature of the manual as a guideline for German officers. It highlights a stark perspective on warfare, where the authors consider the laws of war to be mere formalities, often disregarding humanitarian principles as \"scraps of paper.\" The introduction lays out a systematic discussion of the nature of war, emphasizing the brutal realities and strategies that the German military considers acceptable, effectively setting the stage for a Machiavellian view of military ethics. It discusses the implications of war on civilians, property, and international conduct, preparing the reader for the ensuing detailed examination of wartime practices and principles synthesized from this specific German military perspective. (This is an automatically generated summary.)"], "editors": [], "translators": [{"name": "Morgan, J. H. (John Hartman)", "birth_year": 1876, "death_year": 1955}], "subjects": ["War (International law)", "World War, 1914-1918 -- Law and legislation -- Germany"], "bookshelves": ["Category: German Literature", "Category: History - European", "Category: History - Modern (1750+)", "Category: History - Warfare"], "languages": ["en"], "copyright": false, "media_type": "Text", "formats": {"text/html": "https://www.gutenberg.org/ebooks/51646.html.images", "application/epub+zip": "https://www.gutenberg.org/ebooks/51646.epub3.images", "application/x-mobipocket-ebook": "https://www.gutenberg.org/ebooks/51646.kf8.images", "application/rdf+xml": "https://www.gutenberg.org/ebooks/51646.rdf", "image/jpeg": "https://www.gutenberg.org/cache/epub/51646/pg51646.cover.medium.jpg", "application/octet-stream": "https://www.gutenberg.org/cache/epub/51646/pg51646-h.zip", "text/plain; charset=utf-8": "https://www.gutenberg.org/ebooks/51646.txt.utf-8", "text/plain; charset=us-ascii": "https://www.gutenberg.org/files/51646/51646-0.txt"}, "download_count": 462}