{"id": 52220, "title": "Gedichte der Gefangenen: Ein Sonettenkreis (Nr. 44)", "authors": [{"name": "Toller, Ernst", "birth_year": 1893, "death_year": 1939}], "summaries": ["\"Gedichte der Gefangenen: Ein Sonettenkreis (Nr. 44)\" by Ernst Toller is a collection of poignant sonnets written during the early 20th century, specifically between 1918 and 1921. This book encapsulates the profound and often harrowing experiences of imprisonment, reflecting both personal suffering and broader societal struggles. The thematic focus revolves around the pain of confinement, the longing for freedom, and the collective grief of those who suffer under oppressive regimes.  The content of the collection conveys the emotional and physical trials faced by prisoners, with Toller using vivid language to illustrate their despair and yearning for liberation. Each poem serves as a voice for the unnamed victims of tyranny, exploring themes of loneliness, resistance, and the connection between human beings despite their captivity. Through powerful imagery, Toller evokes the stark contrasts between the beauty of the outside world and the bleakness of prison life, while also recognizing the strength found in unity and shared suffering. The poems resonate as a tribute to the indomitable human spirit in the face of repression, making the collection a timeless reflection on the struggle for freedom and dignity. (This is an automatically generated summary.)"], "editors": [], "translators": [], "subjects": ["German poetry -- 20th century", "World War, 1914-1918 -- Poetry"], "bookshelves": ["Category: German Literature", "Category: Poetry"], "languages": ["de"], "copyright": false, "media_type": "Text", "formats": {"text/html": "https://www.gutenberg.org/ebooks/52220.html.images", "application/epub+zip": "https://www.gutenberg.org/ebooks/52220.epub3.images", "application/x-mobipocket-ebook": "https://www.gutenberg.org/ebooks/52220.kf8.images", "application/rdf+xml": "https://www.gutenberg.org/ebooks/52220.rdf", "image/jpeg": "https://www.gutenberg.org/cache/epub/52220/pg52220.cover.medium.jpg", "application/octet-stream": "https://www.gutenberg.org/cache/epub/52220/pg52220-h.zip", "text/plain; charset=utf-8": "https://www.gutenberg.org/ebooks/52220.txt.utf-8", "text/plain; charset=us-ascii": "https://www.gutenberg.org/files/52220/52220-0.txt"}, "download_count": 344}