{"id": 54200, "title": "Odysseia", "authors": [{"name": "Homer", "birth_year": -750, "death_year": -650}], "summaries": ["\"Odysseia\" by Homer is an ancient Greek epic composed around the 8th or 7th century BC. It follows Odysseus, heroic king of Ithaca, on his perilous ten-year journey home after the Trojan War. All his crewmates perish along the way. Meanwhile, his wife Penelope and son Telemachus struggle against unruly suitors who presume Odysseus dead and compete for Penelope's hand in marriage. This tale of homecoming, wandering, and testing remains one of the oldest surviving works of literature and a cornerstone of the Western canon. (This is an automatically generated summary.)"], "editors": [], "translators": [{"name": "Sj\u00f6str\u00f6m, Axel Gabriel", "birth_year": 1794, "death_year": 1846}], "subjects": ["Epic poetry, Greek -- Translations into Swedish", "Odysseus, King of Ithaca (Mythological character) -- Poetry"], "bookshelves": ["Category: Classics of Literature", "Category: Mythology, Legends & Folklore", "Category: Poetry"], "languages": ["sv"], "copyright": false, "media_type": "Text", "formats": {"text/html": "https://www.gutenberg.org/ebooks/54200.html.images", "application/epub+zip": "https://www.gutenberg.org/ebooks/54200.epub3.images", "application/x-mobipocket-ebook": "https://www.gutenberg.org/ebooks/54200.kf8.images", "application/rdf+xml": "https://www.gutenberg.org/ebooks/54200.rdf", "image/jpeg": "https://www.gutenberg.org/cache/epub/54200/pg54200.cover.medium.jpg", "application/octet-stream": "https://www.gutenberg.org/cache/epub/54200/pg54200-h.zip", "text/plain; charset=utf-8": "https://www.gutenberg.org/ebooks/54200.txt.utf-8", "text/plain; charset=us-ascii": "https://www.gutenberg.org/files/54200/54200-0.txt"}, "download_count": 241}