{"id": 58903, "title": "The Monthly Review of Dental Surgery, No. VIII. October, 1880. Vol. I.: The Journal of the British Dental Association", "authors": [{"name": "Various", "birth_year": null, "death_year": null}], "summaries": ["\"The Monthly Review of Dental Surgery, No. VIII. October, 1880. Vol. I.\" by Various is a scientific publication that was produced during the late 19th century. This journal serves as a crucial record of advancements and discussions in the field of dental surgery, reflecting the status and evolution of dental education and practices of that time. The content primarily focuses on the training and educational requirements for dental surgeons, as well as various dental surgical techniques and innovations.  The publication features essays and papers discussing the importance of thorough education in both general and specialized practices for dental surgeons, with a strong emphasis on proficiency in anatomy and manual skills. It also delves into specific topics such as the transplantation of teeth, the use of dental materials like amalgams, and the insights into dental mechanics vital for effective practice. The articles aim to enhance professional standards and promote cooperation among dentists, showcasing both the challenges and opportunities faced by the dental profession in that era. (This is an automatically generated summary.)"], "editors": [{"name": "Coleman, Alfred", "birth_year": 1828, "death_year": 1902}, {"name": "Walker, Joseph", "birth_year": 1825, "death_year": 1908}], "translators": [], "subjects": ["Dentistry -- Periodicals", "Mouth -- Surgery -- Periodicals"], "bookshelves": ["Category: Health & Medicine", "Category: Journals", "Category: Teaching & Education"], "languages": ["en"], "copyright": false, "media_type": "Text", "formats": {"text/html": "https://www.gutenberg.org/ebooks/58903.html.images", "application/epub+zip": "https://www.gutenberg.org/ebooks/58903.epub3.images", "application/x-mobipocket-ebook": "https://www.gutenberg.org/ebooks/58903.kf8.images", "application/rdf+xml": "https://www.gutenberg.org/ebooks/58903.rdf", "image/jpeg": "https://www.gutenberg.org/cache/epub/58903/pg58903.cover.medium.jpg", "application/octet-stream": "https://www.gutenberg.org/files/58903/58903-0.zip", "text/plain; charset=utf-8": "https://www.gutenberg.org/ebooks/58903.txt.utf-8", "text/plain; charset=us-ascii": "https://www.gutenberg.org/files/58903/58903-0.txt"}, "download_count": 243}