{"id": 6370, "title": "The Story of the Odyssey", "authors": [{"name": "Homer", "birth_year": -750, "death_year": -650}, {"name": "Church, Alfred John", "birth_year": 1829, "death_year": 1912}], "summaries": ["\"The Story of the Odyssey\" by Alfred John Church, adapted from the epic by Homer, is a retelling of a classic ancient Greek poem that has significantly influenced Western literature. Likely written in the late 19th century, this version aims to make the rich narrative accessible to a wider audience, particularly younger readers. The story follows the hero Ulysses (Odysseus) as he embarks on a perilous ten-year journey filled with trials, adventures, and encounters with mythical creatures and divine beings, all while striving to return to his homeland of Ithaca and his faithful wife, Penelope.  The opening of the text introduces the aftermath of the Trojan War, detailing how Ulysses and his fellow warriors begin their return home, only to be thwarted by the wrath of the gods due to various transgressions. In the face of adversity, Athene, the goddess of wisdom, pleads for Ulysses' return to Olympus, showing her compassion for the suffering hero. Meanwhile, Ulysses' son, Telemachus, is depicted in a troubled situation at home, overwhelmed by the suitors vying for his mother\u2019s hand and consuming his father\u2019s estate. As Athene guides him to seek news of his father, the story sets the stage for the exploration of themes such as loyalty, heroism, and the quest for identity in the face of insurmountable odds, highlighting Ulysses' legendary resolve as he navigates the challenges of his journey. (This is an automatically generated summary.)"], "editors": [], "translators": [], "subjects": ["Odysseus, King of Ithaca (Mythological character) -- Juvenile literature"], "bookshelves": ["Category: Adventure", "Category: Classics of Literature", "Category: Mythology, Legends & Folklore"], "languages": ["en"], "copyright": false, "media_type": "Text", "formats": {"text/html": "https://www.gutenberg.org/ebooks/6370.html.images", "application/epub+zip": "https://www.gutenberg.org/ebooks/6370.epub3.images", "application/x-mobipocket-ebook": "https://www.gutenberg.org/ebooks/6370.kf8.images", "application/rdf+xml": "https://www.gutenberg.org/ebooks/6370.rdf", "image/jpeg": "https://www.gutenberg.org/cache/epub/6370/pg6370.cover.medium.jpg", "application/octet-stream": "https://www.gutenberg.org/files/6370/6370.zip", "text/plain; charset=utf-8": "https://www.gutenberg.org/ebooks/6370.txt.utf-8", "text/plain; charset=us-ascii": "https://www.gutenberg.org/files/6370/6370.txt"}, "download_count": 300}