{"id": 6746, "title": "The Grey Fairy Book", "authors": [], "summaries": ["\"The Grey Fairy Book\" by Andrew Lang is a collection of fairy tales derived from various cultures, composed in the late 19th century. This anthology features enchanting stories from Lithuania, Africa, Germany, France, Greece, and more, showcasing the diversity and richness of folklore. Prominent themes include love, magic, adventure, and transformation, with characters often facing challenges that lead them to personal growth or enlightenment.  At the start of the collection, the preface introduces the origin of these tales, emphasizing their cultural variety and the art of storytelling. The first tale, \"Donkey Skin,\" narrates the story of a beloved king who, after the loss of his wife, is compelled to marry again, but only if he finds a woman more beautiful than her. His adopted daughter, fearful of marrying him, seeks the help of her fairy godmother, leading to a series of magical and clever challenges including dresses made of sky, moonbeams, and sunshine. The narrative explores themes of identity, the struggle against unwanted fate, and the ingenuity of the protagonist, setting the tone for the whimsical and moralistic adventures that follow in subsequent tales of the collection. (This is an automatically generated summary.)"], "editors": [{"name": "Lang, Andrew", "birth_year": 1844, "death_year": 1912}], "translators": [], "subjects": ["Fairy tales", "Folklore"], "bookshelves": ["Category: Mythology, Legends & Folklore", "Category: Short Stories", "Children's Literature"], "languages": ["en"], "copyright": false, "media_type": "Text", "formats": {"text/html": "https://www.gutenberg.org/ebooks/6746.html.images", "application/epub+zip": "https://www.gutenberg.org/ebooks/6746.epub3.images", "application/x-mobipocket-ebook": "https://www.gutenberg.org/ebooks/6746.kf8.images", "application/rdf+xml": "https://www.gutenberg.org/ebooks/6746.rdf", "image/jpeg": "https://www.gutenberg.org/cache/epub/6746/pg6746.cover.medium.jpg", "application/octet-stream": "https://www.gutenberg.org/files/6746/6746-0.zip", "text/plain; charset=utf-8": "https://www.gutenberg.org/ebooks/6746.txt.utf-8", "text/plain; charset=us-ascii": "https://www.gutenberg.org/files/6746/6746-0.txt"}, "download_count": 1404}