{"id": 7023, "title": "Rob Roy \u2014 Volume 01", "authors": [{"name": "Scott, Walter", "birth_year": 1771, "death_year": 1832}], "summaries": ["\"Rob Roy \u2014 Volume 01\" by Walter Scott is a historical novel published in 1817. When young Frank Osbaldistone refuses to join his father's merchant business, he's banished to his uncle's estate near the Scottish border. There he falls for the spirited Diana Vernon and becomes entangled in family treachery when his cunning cousin Rashleigh steals vital documents. Frank's pursuit leads him into turbulent Scotland on the eve of the 1715 Jacobite Rising, where he encounters the legendary outlaw Rob Roy MacGregor amid political intrigue and Highland wilderness. (This is an automatically generated summary.)"], "editors": [], "translators": [], "subjects": ["Outlaws -- Fiction", "Rob Roy, 1671-1734 -- Fiction", "Scotland -- History -- 1689-1745 -- Fiction"], "bookshelves": ["Category: British Literature", "Category: Classics of Literature", "Category: Historical Novels", "Historical Fiction"], "languages": ["en"], "copyright": false, "media_type": "Text", "formats": {"text/html": "https://www.gutenberg.org/ebooks/7023.html.images", "application/epub+zip": "https://www.gutenberg.org/ebooks/7023.epub3.images", "application/x-mobipocket-ebook": "https://www.gutenberg.org/ebooks/7023.kf8.images", "application/rdf+xml": "https://www.gutenberg.org/ebooks/7023.rdf", "image/jpeg": "https://www.gutenberg.org/cache/epub/7023/pg7023.cover.medium.jpg", "application/octet-stream": "https://www.gutenberg.org/files/7023/7023-h.zip", "text/plain; charset=utf-8": "https://www.gutenberg.org/ebooks/7023.txt.utf-8", "text/plain; charset=us-ascii": "https://www.gutenberg.org/files/7023/7023.txt"}, "download_count": 434}