{"id": 74637, "title": "Untuvainen : $b Nelin\u00e4yt\u00f6ksinen huvin\u00e4ytelm\u00e4", "authors": [{"name": "Lagerl\u00f6f, Selma", "birth_year": 1858, "death_year": 1940}], "summaries": ["\"Untuvainen: Nelin\u00e4yt\u00f6ksinen huvin\u00e4ytelm\u00e4\" by Selma Lagerl\u00f6f is a theatrical play written in the early 20th century. Set in the 1840s, the narrative unfolds in the house of a factory owner, Teodor Fristedt, and introduces a range of characters including his family, workers, and guests. The story centers around the preparations for a celebration in honor of Mauritz Fristedt, Teodor's nephew, who is engaged to the charming Anne-Marie Ehinger, a baker\u2019s daughter.  The opening of the play depicts a bustling atmosphere as Teodor and his staff prepare for the event, including the humorous idea of adorning the honor gate with a fish. Teodor's interactions reflect his jovial yet whimsical character as he engages in light-hearted banter with his servants and expresses his complicated feelings about his nephew's choice of fianc\u00e9e. Various tensions emerge, particularly regarding social class and family expectations, setting the stage for the broader themes of love, acceptance, and societal norms that may play out in the remainder of the story. (This is an automatically generated summary.)"], "editors": [], "translators": [{"name": "Krohn, Helmi", "birth_year": 1871, "death_year": 1967}], "subjects": ["Swedish drama -- Translations into Finnish"], "bookshelves": ["Nobel Prizes in Literature"], "languages": ["fi"], "copyright": false, "media_type": "Text", "formats": {"text/html": "https://www.gutenberg.org/ebooks/74637.html.images", "application/epub+zip": "https://www.gutenberg.org/ebooks/74637.epub3.images", "application/x-mobipocket-ebook": "https://www.gutenberg.org/ebooks/74637.kf8.images", "application/rdf+xml": "https://www.gutenberg.org/ebooks/74637.rdf", "image/jpeg": "https://www.gutenberg.org/cache/epub/74637/pg74637.cover.medium.jpg", "application/octet-stream": "https://www.gutenberg.org/cache/epub/74637/pg74637-h.zip", "text/plain; charset=utf-8": "https://www.gutenberg.org/ebooks/74637.txt.utf-8", "text/plain; charset=us-ascii": "https://www.gutenberg.org/files/74637/74637-0.txt"}, "download_count": 76}