{"id": 8168, "title": "Gargantua and Pantagruel, Illustrated, Book 3", "authors": [{"name": "Rabelais, Fran\u00e7ois", "birth_year": null, "death_year": null}], "summaries": ["\"Gargantua and Pantagruel, Illustrated, Book 3\" by Fran\u00e7ois Rabelais is a novel written in the 16th century. After settling Panurge's debts, Pantagruel faces a new challenge: his companion suddenly wants to marry but cannot decide if he should. They consult fortune-tellers, scholars, poets, and philosophers, yet Panurge rejects every answer. Finally, they resolve to seek wisdom from the Divine Bottle itself, setting sail on an extraordinary voyage that will test their wits and friendship. (This is an automatically generated summary.)"], "editors": [], "translators": [{"name": "Motteux, Peter Anthony", "birth_year": 1660, "death_year": 1718}, {"name": "Urquhart, Thomas, Sir", "birth_year": 1611, "death_year": 1660}], "subjects": ["Fantasy fiction, French -- Translations into English", "Gargantua (Legendary character) -- Fiction", "Giants -- Fiction"], "bookshelves": ["Best Books Ever Listings", "Category: French Literature", "Category: Humour", "Category: Novels"], "languages": ["en"], "copyright": false, "media_type": "Text", "formats": {"text/html": "https://www.gutenberg.org/ebooks/8168.html.images", "application/epub+zip": "https://www.gutenberg.org/ebooks/8168.epub3.images", "application/x-mobipocket-ebook": "https://www.gutenberg.org/ebooks/8168.kf8.images", "application/rdf+xml": "https://www.gutenberg.org/ebooks/8168.rdf", "image/jpeg": "https://www.gutenberg.org/cache/epub/8168/pg8168.cover.medium.jpg", "application/octet-stream": "https://www.gutenberg.org/files/8168/8168-h.zip", "text/plain; charset=utf-8": "https://www.gutenberg.org/ebooks/8168.txt.utf-8", "text/plain; charset=us-ascii": "https://www.gutenberg.org/files/8168/8168.txt"}, "download_count": 927}