{"id": 8687, "title": "Scientific American Supplement, No. 362, December 9, 1882", "authors": [{"name": "Various", "birth_year": null, "death_year": null}], "summaries": ["\"Scientific American Supplement, No. 362, December 9, 1882\" by Various is a scientific publication written during the late 19th century. This periodical presents a compilation of articles covering various advancements and discussions in fields such as engineering, technology, chemistry, hygiene, electricity, metallurgy, architecture, and botany, reflecting the scientific progress and interests of the time.  At the start of this supplement, readers are introduced to a wide array of topics. The content includes recent improvements in textile machinery, the significant contributions of chemist Friedrich W\u00f6hler, advancements in electric lighting, and the construction and functionality of a new rolling mill for iron. There are also insights into public health and hygiene, specifically related to the quality of air and its impact on health. Through detailed illustrations and technical descriptions, the opening portion showcases notable innovations and analyses, signifying the intersection of science and industry during the late 19th century. (This is an automatically generated summary.)"], "editors": [], "translators": [], "subjects": ["Science -- Periodicals"], "bookshelves": ["Category: Architecture", "Category: Engineering & Technology", "Category: Reports & Conference Proceedings", "Category: Science - Chemistry/Biochemistry", "Category: Science - Earth/Agricultural/Farming", "Scientific American"], "languages": ["en"], "copyright": false, "media_type": "Text", "formats": {"text/html": "https://www.gutenberg.org/ebooks/8687.html.images", "application/epub+zip": "https://www.gutenberg.org/ebooks/8687.epub3.images", "application/x-mobipocket-ebook": "https://www.gutenberg.org/ebooks/8687.kf8.images", "application/rdf+xml": "https://www.gutenberg.org/ebooks/8687.rdf", "image/jpeg": "https://www.gutenberg.org/cache/epub/8687/pg8687.cover.medium.jpg", "application/octet-stream": "https://www.gutenberg.org/files/8687/8687-8.zip", "text/plain; charset=utf-8": "https://www.gutenberg.org/ebooks/8687.txt.utf-8", "text/plain; charset=us-ascii": "https://www.gutenberg.org/files/8687/8687-8.txt"}, "download_count": 344}