{"id": 9666, "title": "Scientific American Supplement, No. 497, July 11, 1885", "authors": [{"name": "Various", "birth_year": null, "death_year": null}], "summaries": ["\"Scientific American Supplement, No. 497, July 11, 1885\" by Various is a scientific publication likely produced during the late 19th century. This volume is part of a series aimed at disseminating knowledge on various scientific and technological advancements of its time, covering diverse topics from chemistry to engineering, natural history to botany.  The opening portion of this edition includes several articles discussing topics such as the processes for making sea water potable, the intricacies of building foundations in quicksand, and advancements in engineering highlighted by a detailed description of a lift bridge over the Ourcq Canal. These articles provide insights into the innovative practices and technical challenges of the era, as well as detailing achievements in transportation and infrastructure, showcasing how scientific principles were applied to solve real-world problems. The beginning of this publication thus sets the stage for discussions that illustrate the blend of science, technology, and engineering prevalent in the late 19th century. (This is an automatically generated summary.)"], "editors": [], "translators": [], "subjects": ["Science -- Periodicals"], "bookshelves": ["Category: Engineering & Technology", "Category: Journals", "Category: Science - Chemistry/Biochemistry", "Category: Science - Earth/Agricultural/Farming", "Scientific American"], "languages": ["en"], "copyright": false, "media_type": "Text", "formats": {"text/html": "https://www.gutenberg.org/ebooks/9666.html.images", "application/epub+zip": "https://www.gutenberg.org/ebooks/9666.epub3.images", "application/x-mobipocket-ebook": "https://www.gutenberg.org/ebooks/9666.kf8.images", "application/rdf+xml": "https://www.gutenberg.org/ebooks/9666.rdf", "image/jpeg": "https://www.gutenberg.org/cache/epub/9666/pg9666.cover.medium.jpg", "application/octet-stream": "https://www.gutenberg.org/files/9666/9666-8.zip", "text/plain; charset=utf-8": "https://www.gutenberg.org/ebooks/9666.txt.utf-8", "text/plain; charset=us-ascii": "https://www.gutenberg.org/files/9666/9666-8.txt"}, "download_count": 268}